supercube/NCube.py
supercube/PocketCube.py
supercube/RubiksCube.py
supercube/__init__.py
supercube/cube.py
supercube/kociemba/__init__.py
supercube/kociemba/build_ckociemba.py
supercube/kociemba/command_line.py
supercube/kociemba/pykociemba/__init__.py
supercube/kociemba/pykociemba/color.py
supercube/kociemba/pykociemba/coordcube.py
supercube/kociemba/pykociemba/corner.py
supercube/kociemba/pykociemba/cubiecube.py
supercube/kociemba/pykociemba/edge.py
supercube/kociemba/pykociemba/facecube.py
supercube/kociemba/pykociemba/facelet.py
supercube/kociemba/pykociemba/search.py
supercube/kociemba/pykociemba/tools.py
supercube/kociemba/pykociemba/prunetables/FRtoBR_Move.pkl
supercube/kociemba/pykociemba/prunetables/MergeURtoULandUBtoDF.pkl
supercube/kociemba/pykociemba/prunetables/Slice_Flip_Prun.pkl
supercube/kociemba/pykociemba/prunetables/Slice_Twist_Prun.pkl
supercube/kociemba/pykociemba/prunetables/Slice_URFtoDLF_Parity_Prun.pkl
supercube/kociemba/pykociemba/prunetables/Slice_URtoDF_Parity_Prun.pkl
supercube/kociemba/pykociemba/prunetables/UBtoDF_Move.pkl
supercube/kociemba/pykociemba/prunetables/URFtoDLF_Move.pkl
supercube/kociemba/pykociemba/prunetables/URtoDF_Move.pkl
supercube/kociemba/pykociemba/prunetables/URtoUL_Move.pkl
supercube/kociemba/pykociemba/prunetables/flipMove.pkl
supercube/kociemba/pykociemba/prunetables/twistMove.pkl
supercube/kociemba_2x2/__init__.py
supercube/kociemba_2x2/client_gui.py
supercube/kociemba_2x2/coord.py
supercube/kociemba_2x2/cubie.py
supercube/kociemba_2x2/defs.py
supercube/kociemba_2x2/enums.py
supercube/kociemba_2x2/example.py
supercube/kociemba_2x2/face.py
supercube/kociemba_2x2/misc.py
supercube/kociemba_2x2/moves.py
supercube/kociemba_2x2/pruning.py
supercube/kociemba_2x2/sockets.py
supercube/kociemba_2x2/solver.py
supercube/kociemba_2x2/start_server.py
super_rubik_cube-1.0.53.dist-info/LICENSE
super_rubik_cube-1.0.53.dist-info/METADATA
super_rubik_cube-1.0.53.dist-info/WHEEL
super_rubik_cube-1.0.53.dist-info/top_level.txt
super_rubik_cube-1.0.53.dist-info/RECORD
