Metadata-Version: 2.1
Name: super-rubik-cube
Version: 1.0.53
Summary: Library for simulating rubik's cubes of different sizes (N x N), for solving 2 x 2 and 3 x 3 cubes with kociemba algorithm, and for 3D visualization of cubes.
Author: Ilmi28
Author-email: <ilmialiev28@gmail.com>
License: GPL-3.0
Project-URL: Homepage, https://github.com/Ilmi28/SuperCube
Keywords: python,rubik,cube,solve,3x3,2x2,rubik's cube,pocket cube,NxN,kociemba,supercube,solver,3D,jupyter
License-File: LICENSE
Requires-Dist: pyvista[jupyter] ==0.43.10
Requires-Dist: numpy <2
Requires-Dist: pythreejs
Requires-Dist: ipywidgets
